sres-1.0.1.data/purelib/sres/__init__.py
sres-1.0.1.data/purelib/sres/libSRESC.so
sres-1.0.1.data/purelib/sres/sres.py
sres-1.0.1.dist-info/METADATA
sres-1.0.1.dist-info/WHEEL
sres-1.0.1.dist-info/top_level.txt
sres-1.0.1.dist-info/RECORD
