Metadata-Version: 2.1
Name: sres
Version: 1.0.1
Summary: UNKNOWN
Home-page: https://github.com/sys-bio/SRES
Author: Ciaran Welsh
Author-email: cw00137@gmail.com
License: MIT
Keywords: parameter estimation
Platform: Windows
Platform: Unix
Platform: Mac OS-X
Requires-Dist: numpy
Requires-Dist: pandas
Requires-Dist: pywin32 ; sys_platform == "Windows"
